miscutils/__init__.py
miscutils/logging_config.py
miscutils/middleware.py
miscutils/testing.py
miscutils/timer.py
misc_utils_py-0.3.0.dist-info/LICENSE
misc_utils_py-0.3.0.dist-info/WHEEL
misc_utils_py-0.3.0.dist-info/METADATA
misc_utils_py-0.3.0.dist-info/RECORD
