Metadata-Version: 2.1
Name: misc-utils-py
Version: 0.3.0
Summary: Misc utilities for python projects.
Home-page: https://github.com/dbradf/misc-utils-py
License: Apache-2.0
Author: Alexander Costas
Author-email: alexander.costas@mongodb.com
Requires-Python: >=3.7,<4.0
Classifier: License :: OSI Approved :: Apache Software License
Classifier: Programming Language :: Python :: 3
Classifier: Programming Language :: Python :: 3.7
Classifier: Programming Language :: Python :: 3.8
Requires-Dist: python-json-logger (>=0.1,<0.2)
Requires-Dist: starlette (>=0.13,<0.14)
Requires-Dist: structlog (>=19,<20)
Project-URL: Repository, https://github.com/dbradf/misc-utils-py
